templateengine/TemplateEngine.py
templateengine/__init__.py
templateengine/main.py
templateengine/ai/IModel.py
templateengine/ai/IPromptBuilder.py
templateengine/ai/ISession.py
templateengine/ai/OpenAIModel.py
templateengine/ai/OpenAISession.py
templateengine/ai/__init__.py
templateengine/build/AIModelsFactory.py
templateengine/build/ExecutorsFactory.py
templateengine/build/PlannersFactory.py
templateengine/build/StrategiesFactory.py
templateengine/build/TemplateEngineFactory.py
templateengine/build/ToolsFactory.py
templateengine/build/__init__.py
templateengine/cmd/CommandLineInput.py
templateengine/cmd/CommandLineOutput.py
templateengine/cmd/__init__.py
templateengine/config/config.yml
templateengine/container/TemplateEngineProcess.py
templateengine/container/__init__.py
templateengine/data/CommandType.py
templateengine/data/CustomSpinner.py
templateengine/data/ICustomSpinner.py
templateengine/data/InputParams.py
templateengine/data/OutputStream.py
templateengine/data/__init__.py
templateengine/data/errors/ErrorHandling.py
templateengine/data/errors/ExecError.py
templateengine/data/errors/IErrorHandling.py
templateengine/data/errors/__init__.py
templateengine/exec/Action.py
templateengine/exec/Executor.py
templateengine/exec/IExecutor.py
templateengine/exec/__init__.py
templateengine/exec/operations/CommonOperation.py
templateengine/exec/operations/CopyAllOperation.py
templateengine/exec/operations/CopyDirOperation.py
templateengine/exec/operations/CopyFileOperation.py
templateengine/exec/operations/CreateDirOperation.py
templateengine/exec/operations/CreateFileOperation.py
templateengine/exec/operations/DeleteDirOperation.py
templateengine/exec/operations/DeleteFileOperation.py
templateengine/exec/operations/EditContentOperation.py
templateengine/exec/operations/IOperation.py
templateengine/exec/operations/RenameDirOperation.py
templateengine/exec/operations/RenameFileOperation.py
templateengine/exec/operations/__init__.py
templateengine/exec/tools/CommonTool.py
templateengine-2.0.6.dist-info/LICENSE
templateengine-2.0.6.dist-info/METADATA
templateengine-2.0.6.dist-info/WHEEL
templateengine-2.0.6.dist-info/entry_points.txt
templateengine-2.0.6.dist-info/top_level.txt
templateengine-2.0.6.dist-info/zip-safe
templateengine-2.0.6.dist-info/RECORD
