Metadata-Version: 2.2
Name: templateengine
Version: 2.0.6
Summary: Template Engine V2 - Create software component skeletons from templates and generate new components with AI-assisted tools.
Home-page: https://bitbucket.org/entinco/eic-templateengine/src/master/cmd-templateengine2-python
Author: Conceptual Vision Consulting LLC
Author-email: seroukhov@gmail.com
License: Commercial
Platform: any
Classifier: Intended Audience :: Developers
Classifier: License :: Other/Proprietary License
Classifier: Operating System :: OS Independent
Classifier: Programming Language :: Python
Classifier: Programming Language :: Python :: 3.12
Classifier: Programming Language :: Python :: 3.12
Classifier: Programming Language :: Python :: 3.12
Classifier: Programming Language :: Python :: 3.12
Classifier: Topic :: Software Development :: Libraries :: Python Modules
License-File: LICENSE
Dynamic: author
Dynamic: author-email
Dynamic: classifier
Dynamic: description
Dynamic: description-content-type
Dynamic: home-page
Dynamic: license
Dynamic: platform
Dynamic: summary
